awscli_plugin_passtotp/__init__.py
awscli_plugin_passtotp/boto_plugin.py
awscli_plugin_passtotp/commands.py
awscli_plugin_passtotp/prompter.py
awscli_plugin_passtotp-1.0.2.dist-info/METADATA
awscli_plugin_passtotp-1.0.2.dist-info/WHEEL
awscli_plugin_passtotp-1.0.2.dist-info/RECORD
