Metadata-Version: 2.1
Name: awscli-plugin-passtotp
Version: 1.0.2
Summary: 
Home-page: https://git.segundo.io/awscli-plugin-passtotp
License: GPL-3.0-or-later
Keywords: aws,aws-cli,boto3,pass,pass-otp
Author: Christian Segundo
Author-email: christian@segundo.com
Requires-Python: >=3.7,<4.0
Classifier: Environment :: Console
Classifier: Intended Audience :: Developers
Classifier: Intended Audience :: System Administrators
Classifier: License :: OSI Approved :: GNU General Public License v3 or later (GPLv3+)
Classifier: Programming Language :: Python :: 3
Classifier: Programming Language :: Python :: 3.7
Classifier: Programming Language :: Python :: 3.8
Classifier: Programming Language :: Python :: 3.9
Classifier: Programming Language :: Python :: 3.10
Classifier: Programming Language :: Python :: 3.11
Requires-Dist: botocore (>=1.14.14,<2.0.0)
Project-URL: Documentation, https://git.segundo.io/awscli-plugin-passtotp/tree/README
Project-URL: Repository, https://git.segundo.io/awscli-plugin-passtotp
